halftonesfc/__init__.py
halftonesfc/cli.py
halftonesfc/halftone.py
halftonesfc/sfc.py
halftonesfc-0.1.2.dist-info/LICENSE
halftonesfc-0.1.2.dist-info/METADATA
halftonesfc-0.1.2.dist-info/WHEEL
halftonesfc-0.1.2.dist-info/dependency_links.txt
halftonesfc-0.1.2.dist-info/entry_points.txt
halftonesfc-0.1.2.dist-info/top_level.txt
halftonesfc-0.1.2.dist-info/RECORD
