Metadata-Version: 2.2
Name: halftonesfc
Version: 0.1.2
Summary: A Python package for Digital Halftoning with Space Filling Curves
Author: halftonesfc-team
Author-email: al.pedro.porto@impatech.org.br
Classifier: Programming Language :: Python :: 3
Classifier: License :: OSI Approved :: MIT License
Classifier: Operating System :: OS Independent
License-File: LICENSE
Requires-Dist: opencv-python
Requires-Dist: matplotlib
Requires-Dist: numpy
Dynamic: author
Dynamic: author-email
Dynamic: classifier
Dynamic: description
Dynamic: description-content-type
Dynamic: requires-dist
Dynamic: summary
